LICENSE
MANIFEST.in
requirements.txt
setup.py
imagefy/__init__.py
imagefy/client.py
imagefy/exceptions.py
imagefy/filters.py
imagefy/models.py
imagefy.egg-info/PKG-INFO
imagefy.egg-info/SOURCES.txt
imagefy.egg-info/dependency_links.txt
imagefy.egg-info/requires.txt
imagefy.egg-info/top_level.txt