Metadata-Version: 1.0
Name: imagefy
Version: 1.0.6
Summary: A Python wrapper for the Imagefy API.
Home-page: https://bitbucket.org/singster/imagefy-sdk-python
Author: Atte Valtonen
Author-email: atte.valtonen@sin.ga
License: MIT
Platform: UNKNOWN
